multitrans/__init__.py
multitrans/core.py
multitrans-1.0.0.dist-info/METADATA
multitrans-1.0.0.dist-info/RECORD
multitrans-1.0.0.dist-info/WHEEL
multitrans-1.0.0.dist-info/top_level.txt
multrans/__init__.py
multrans/core.py
