Metadata-Version: 2.1
Name: multitrans
Version: 1.0.0
Summary: Translate multiple strings to multiple languages using Google Translate
Home-page: https://github.com/AlexNilsson/python-google-translate
Author: Alexander Nilsson
Author-email: contact@alexnilsson.io
License: MIT
Keywords: google translate multiple languages
Platform: UNKNOWN
Requires-Dist: setuptools (>=28.8.0)
